plover_cards/__init__.py
plover_cards/anki_utils.py
plover_cards/config.py
plover_cards/resources_rc.py
plover_cards/card_builder/__init__.py
plover_cards/card_builder/card_builder.py
plover_cards/card_builder/card_builder_ui.py
plover_cards/card_builder/card_table_model.py
plover_cards/card_builder/cards.py
plover_cards/card_builder/resources_rc.py
plover_cards/card_builder/utils.py
plover_cards/commands/__init__.py
plover_cards/commands/anki_commands.py
plover_cards/plover_hook/__init__.py
plover_cards/plover_hook/card_suggestions.py
plover_cards/plover_hook/plover_hook.py
plover_cards-0.2.1.post2.dist-info/LICENSE
plover_cards-0.2.1.post2.dist-info/METADATA
plover_cards-0.2.1.post2.dist-info/WHEEL
plover_cards-0.2.1.post2.dist-info/entry_points.txt
plover_cards-0.2.1.post2.dist-info/top_level.txt
plover_cards-0.2.1.post2.dist-info/zip-safe
plover_cards-0.2.1.post2.dist-info/RECORD
