Metadata-Version: 2.1
Name: plover-cards
Version: 0.2.1.post2
Summary: Helps build a CSV of new words and stroke improvements for your Anki deck.
Home-page: https://github.com/antistic/plover_cards
Author: Antonia Siu
Author-email: hello@antoniasiu.co.uk
License: GNU General Public License v3 (GPLv3)
Project-URL: Issues, https://github.com/antistic/plover_cards/issues
Keywords: plover plover_plugin anki
Platform: UNKNOWN
Classifier: Development Status :: 4 - Beta
Classifier: Environment :: Plugins
Classifier: Intended Audience :: End Users/Desktop
Classifier: License :: OSI Approved :: GNU General Public License v3 (GPLv3)
Classifier: Operating System :: OS Independent
Classifier: Programming Language :: Python :: 3
Classifier: Programming Language :: Python :: 3.7
Classifier: Programming Language :: Python :: 3.8
Classifier: Programming Language :: Python :: 3.9
Requires-Python: >=3.7
Requires-Dist: plover[gui_qt] (>=4.0.0.dev3)
